<?xml version="1.0" encoding="UTF-8"?>
<mesh>
    <sharedgeometry vertexcount="24">
        <vertexbuffer texture_coords="1" positions="true" colours_diffuse="False" normals="true">
            <vertex>
                <position y="-0.008876" x="23.249033" z="-26.590042"/>
                <normal y="-1.000000" x="0.000000" z="-0.000000"/>
                <texcoord u="0.987471" v="1.000970"/>
            </vertex>
            <vertex>
                <position y="-0.008876" x="23.249033" z="21.681992"/>
                <normal y="-1.000000" x="0.000000" z="-0.000000"/>
                <texcoord u="0.008103" v="1.000970"/>
            </vertex>
            <vertex>
                <position y="-0.008876" x="20.414692" z="21.681986"/>
                <normal y="-1.000000" x="0.000000" z="-0.000000"/>
                <texcoord u="0.008104" v="1.000970"/>
            </vertex>
            <vertex>
                <position y="-0.008876" x="20.414692" z="-26.590046"/>
                <normal y="-1.000000" x="0.000000" z="-0.000000"/>
                <texcoord u="0.987471" v="1.000970"/>
            </vertex>
            <vertex>
                <position y="28.766390" x="23.249033" z="-26.590033"/>
                <normal y="1.000000" x="0.000000" z="0.000000"/>
                <texcoord u="0.976971" v="0.010397"/>
            </vertex>
            <vertex>
                <position y="28.766390" x="20.414692" z="-26.590042"/>
                <normal y="1.000000" x="0.000000" z="0.000000"/>
                <texcoord u="0.976971" v="0.010397"/>
            </vertex>
            <vertex>
                <position y="28.766390" x="20.414692" z="21.681984"/>
                <normal y="1.000000" x="0.000000" z="0.000000"/>
                <texcoord u="-0.002396" v="0.010397"/>
            </vertex>
            <vertex>
                <position y="28.766390" x="23.249033" z="21.681995"/>
                <normal y="1.000000" x="0.000000" z="0.000000"/>
                <texcoord u="-0.002396" v="0.010397"/>
            </vertex>
            <vertex>
                <position y="-0.008876" x="23.249033" z="-26.590042"/>
                <normal y="0.000000" x="1.000000" z="0.000000"/>
                <texcoord u="0.479323" v="0.279104"/>
            </vertex>
            <vertex>
                <position y="28.766390" x="23.249033" z="-26.590033"/>
                <normal y="0.000000" x="1.000000" z="0.000000"/>
                <texcoord u="0.479323" v="-0.720896"/>
            </vertex>
            <vertex>
                <position y="28.766390" x="23.249033" z="21.681995"/>
                <normal y="0.000000" x="1.000000" z="0.000000"/>
                <texcoord u="-0.429352" v="-0.720896"/>
            </vertex>
            <vertex>
                <position y="-0.008876" x="23.249033" z="21.681992"/>
                <normal y="0.000000" x="1.000000" z="0.000000"/>
                <texcoord u="-0.429352" v="0.279104"/>
            </vertex>
            <vertex>
                <position y="-0.008876" x="23.249033" z="21.681992"/>
                <normal y="-0.000000" x="-0.000003" z="1.000000"/>
                <texcoord u="0.008103" v="1.000970"/>
            </vertex>
            <vertex>
                <position y="28.766390" x="23.249033" z="21.681995"/>
                <normal y="-0.000000" x="-0.000003" z="1.000000"/>
                <texcoord u="-0.002396" v="0.010397"/>
            </vertex>
            <vertex>
                <position y="28.766390" x="20.414692" z="21.681984"/>
                <normal y="-0.000000" x="-0.000003" z="1.000000"/>
                <texcoord u="-0.002396" v="0.010397"/>
            </vertex>
            <vertex>
                <position y="-0.008876" x="20.414692" z="21.681986"/>
                <normal y="-0.000000" x="-0.000003" z="1.000000"/>
                <texcoord u="0.008104" v="1.000970"/>
            </vertex>
            <vertex>
                <position y="-0.008876" x="20.414692" z="21.681986"/>
                <normal y="0.000000" x="-1.000000" z="0.000000"/>
                <texcoord u="0.008104" v="1.000970"/>
            </vertex>
            <vertex>
                <position y="28.766390" x="20.414692" z="21.681984"/>
                <normal y="0.000000" x="-1.000000" z="0.000000"/>
                <texcoord u="-0.002396" v="0.010397"/>
            </vertex>
            <vertex>
                <position y="28.766390" x="20.414692" z="-26.590042"/>
                <normal y="0.000000" x="-1.000000" z="0.000000"/>
                <texcoord u="0.976971" v="0.010397"/>
            </vertex>
            <vertex>
                <position y="-0.008876" x="20.414692" z="-26.590046"/>
                <normal y="0.000000" x="-1.000000" z="0.000000"/>
                <texcoord u="0.987471" v="1.000970"/>
            </vertex>
            <vertex>
                <position y="28.766390" x="23.249033" z="-26.590033"/>
                <normal y="0.000000" x="0.000002" z="-1.000000"/>
                <texcoord u="0.976971" v="0.010397"/>
            </vertex>
            <vertex>
                <position y="-0.008876" x="23.249033" z="-26.590042"/>
                <normal y="0.000000" x="0.000002" z="-1.000000"/>
                <texcoord u="0.987471" v="1.000970"/>
            </vertex>
            <vertex>
                <position y="-0.008876" x="20.414692" z="-26.590046"/>
                <normal y="0.000000" x="0.000002" z="-1.000000"/>
                <texcoord u="0.987471" v="1.000970"/>
            </vertex>
            <vertex>
                <position y="28.766390" x="20.414692" z="-26.590042"/>
                <normal y="0.000000" x="0.000002" z="-1.000000"/>
                <texcoord u="0.976971" v="0.010397"/>
            </vertex>
        </vertexbuffer>
    </sharedgeometry>
    <submeshes>
        <submesh usesharedvertices="true" material="matWall2" use32bitindexes="False" operationtype="triangle_list">
            <faces count="10">
                <face v1="0" v2="1" v3="2"/>
                <face v1="0" v2="2" v3="3"/>
                <face v1="4" v2="5" v3="6"/>
                <face v1="4" v2="6" v3="7"/>
                <face v1="12" v2="13" v3="14"/>
                <face v1="12" v2="14" v3="15"/>
                <face v1="16" v2="17" v3="18"/>
                <face v1="16" v2="18" v3="19"/>
                <face v1="20" v2="21" v3="22"/>
                <face v1="20" v2="22" v3="23"/>
            </faces>
        </submesh>
        <submesh usesharedvertices="true" material="matWall3" use32bitindexes="False" operationtype="triangle_list">
            <faces count="2">
                <face v1="8" v2="9" v3="10"/>
                <face v1="8" v2="10" v3="11"/>
            </faces>
        </submesh>
    </submeshes>
    <submeshnames>
        <submesh index="0" name="matWall1">
        </submesh>
        <submesh index="1" name="matWall2">
        </submesh>
        <submesh index="2" name="matWall3">
        </submesh>
        <submesh index="3" name="matWall4">
        </submesh>
    </submeshnames>
</mesh>